LICENSE
README.rst
setup.py
steam/__init__.py
steam/exceptions.py
steam/game_servers.py
steam/globalid.py
steam/guard.py
steam/monkey.py
steam/steamid.py
steam/webapi.py
steam/webauth.py
steam/client/__init__.py
steam/client/cdn.py
steam/client/gc.py
steam/client/user.py
steam/client/builtins/__init__.py
steam/client/builtins/apps.py
steam/client/builtins/friends.py
steam/client/builtins/gameservers.py
steam/client/builtins/leaderboards.py
steam/client/builtins/unified_messages.py
steam/client/builtins/user.py
steam/client/builtins/web.py
steam/core/__init__.py
steam/core/cm.py
steam/core/connection.py
steam/core/crypto.py
steam/core/manifest.py
steam/core/msg/__init__.py
steam/core/msg/headers.py
steam/core/msg/structs.py
steam/core/msg/unified.py
steam/enums/__init__.py
steam/enums/base.py
steam/enums/common.py
steam/enums/emsg.py
steam/enums/proto.py
steam/protobufs/__init__.py
steam/protobufs/content_manifest_pb2.py
steam/protobufs/encrypted_app_ticket_pb2.py
steam/protobufs/enums_clientserver_pb2.py
steam/protobufs/enums_pb2.py
steam/protobufs/enums_productinfo_pb2.py
steam/protobufs/gc_pb2.py
steam/protobufs/offline_ticket_pb2.py
steam/protobufs/steammessages_auth_pb2.py
steam/protobufs/steammessages_base_pb2.py
steam/protobufs/steammessages_broadcast_pb2.py
steam/protobufs/steammessages_chat_pb2.py
steam/protobufs/steammessages_client_objects_pb2.py
steam/protobufs/steammessages_clientserver_2_pb2.py
steam/protobufs/steammessages_clientserver_appinfo_pb2.py
steam/protobufs/steammessages_clientserver_friends_pb2.py
steam/protobufs/steammessages_clientserver_gameservers_pb2.py
steam/protobufs/steammessages_clientserver_lbs_pb2.py
steam/protobufs/steammessages_clientserver_login_pb2.py
steam/protobufs/steammessages_clientserver_mms_pb2.py
steam/protobufs/steammessages_clientserver_pb2.py
steam/protobufs/steammessages_clientserver_ucm_pb2.py
steam/protobufs/steammessages_clientserver_uds_pb2.py
steam/protobufs/steammessages_clientserver_ufs_pb2.py
steam_dst.egg-info/PKG-INFO
steam_dst.egg-info/SOURCES.txt
steam_dst.egg-info/dependency_links.txt
steam_dst.egg-info/requires.txt
steam_dst.egg-info/top_level.txt
steam_dst.egg-info/zip-safe
